odoo10_addon_queue_job-10.0.1.2.0-py3.6-nspkg.pth
odoo/addons/queue_job/README.rst
odoo/addons/queue_job/__init__.py
odoo/addons/queue_job/__manifest__.py
odoo/addons/queue_job/exception.py
odoo/addons/queue_job/fields.py
odoo/addons/queue_job/job.py
odoo/addons/queue_job/controllers/__init__.py
odoo/addons/queue_job/controllers/main.py
odoo/addons/queue_job/data/queue_data.xml
odoo/addons/queue_job/i18n/queue_job.pot
odoo/addons/queue_job/jobrunner/__init__.py
odoo/addons/queue_job/jobrunner/channels.py
odoo/addons/queue_job/jobrunner/runner.py
odoo/addons/queue_job/migrations/10.0.1.0.0/end-migration.py
odoo/addons/queue_job/migrations/10.0.1.0.0/post-migration.py
odoo/addons/queue_job/migrations/10.0.1.0.0/pre-migration.py
odoo/addons/queue_job/models/__init__.py
odoo/addons/queue_job/models/base.py
odoo/addons/queue_job/models/queue_job.py
odoo/addons/queue_job/readme/CONFIGURE.rst
odoo/addons/queue_job/readme/CONTRIBUTORS.rst
odoo/addons/queue_job/readme/DESCRIPTION.rst
odoo/addons/queue_job/readme/HISTORY.rst
odoo/addons/queue_job/readme/INSTALL.rst
odoo/addons/queue_job/readme/ROADMAP.rst
odoo/addons/queue_job/readme/USAGE.rst
odoo/addons/queue_job/security/ir.model.access.csv
odoo/addons/queue_job/security/security.xml
odoo/addons/queue_job/static/description/icon.png
odoo/addons/queue_job/static/description/icon.svg
odoo/addons/queue_job/static/description/index.html
odoo/addons/queue_job/tests/__init__.py
odoo/addons/queue_job/tests/common.py
odoo/addons/queue_job/tests/test_json_field.py
odoo/addons/queue_job/tests/test_model_job_channel.py
odoo/addons/queue_job/tests/test_runner_channels.py
odoo/addons/queue_job/tests/test_runner_runner.py
odoo/addons/queue_job/views/queue_job_views.xml
odoo10_addon_queue_job-10.0.1.2.0.dist-info/METADATA
odoo10_addon_queue_job-10.0.1.2.0.dist-info/WHEEL
odoo10_addon_queue_job-10.0.1.2.0.dist-info/namespace_packages.txt
odoo10_addon_queue_job-10.0.1.2.0.dist-info/top_level.txt
odoo10_addon_queue_job-10.0.1.2.0.dist-info/RECORD
